LICENSE
README.md
pyproject.toml
setup.py
./ringbuf/__init__.py
./ringbuf/boost.pxd
./ringbuf/libc_constants.pyx
./ringbuf/ringbufcy.pxd
./ringbuf/ringbufcy.pyx
ringbuf/libc_constants.c
ringbuf/ringbufcy.cpp
ringbuf.egg-info/PKG-INFO
ringbuf.egg-info/SOURCES.txt
ringbuf.egg-info/dependency_links.txt
ringbuf.egg-info/not-zip-safe
ringbuf.egg-info/requires.txt
ringbuf.egg-info/top_level.txt
test/test.py