Metadata-Version: 2.1
Name: ringbuf
Version: 2.6.0
Summary: A lock-free ring buffer for Python and Cython
Author-email: Elijah Shaw-Rutschman <elijahr+ringbuf@gmail.com>
Maintainer-email: Elijah Shaw-Rutschman <elijahr+ringbuf@gmail.com>
License: MIT License
Project-URL: GitHub, https://github.com/elijahr/ringbuf
Project-URL: PyPI, https://pypi.org/ringbuf
Keywords: ring buffer,ringbuffer,ringbuf,circular buffer,lock free,queue,dsp,cython
Classifier: Operating System :: MacOS :: MacOS X
Classifier: Operating System :: POSIX :: Linux
Classifier: Operating System :: Microsoft :: Windows
Classifier: Programming Language :: Cython
Classifier: Programming Language :: Python :: 3
Classifier: Programming Language :: Python :: Implementation :: PyPy
Classifier: Programming Language :: Python :: Implementation :: CPython
Classifier: Topic :: Multimedia :: Sound/Audio
Classifier: License :: OSI Approved :: MIT License
Requires-Python: >=3.6
Provides-Extra: dev
License-File: LICENSE
